primo/__init__.py
maglezprimo-0.1.1.dist-info/LICENSE.txt
maglezprimo-0.1.1.dist-info/METADATA
maglezprimo-0.1.1.dist-info/WHEEL
maglezprimo-0.1.1.dist-info/top_level.txt
maglezprimo-0.1.1.dist-info/RECORD
